flask_reqcheck/__init__.py
flask_reqcheck/decorators.py
flask_reqcheck/extension.py
flask_reqcheck/request_validation.py
flask_reqcheck/valid_request.py
flask_reqcheck/validation_utils.py
flask_reqcheck-0.0.11.dist-info/LICENSE
flask_reqcheck-0.0.11.dist-info/METADATA
flask_reqcheck-0.0.11.dist-info/WHEEL
flask_reqcheck-0.0.11.dist-info/top_level.txt
flask_reqcheck-0.0.11.dist-info/RECORD
