Metadata-Version: 2.1
Name: flask-reqcheck
Version: 0.0.11
Summary: Request validation for Flask applications using Pydantic.
Author: Lewis Dunne
Keywords: Python,Flask,validation
Classifier: Programming Language :: Python :: 3
Classifier: License :: OSI Approved :: MIT License
Classifier: Operating System :: OS Independent
Requires-Python: >=3.11
License-File: LICENSE
Requires-Dist: Flask
Requires-Dist: pydantic
Provides-Extra: dev
Requires-Dist: black ; extra == 'dev'
Requires-Dist: isort ; extra == 'dev'
Requires-Dist: numpydoc ; extra == 'dev'
Requires-Dist: Pallets-Sphinx-Themes ; extra == 'dev'
Requires-Dist: pytest ; extra == 'dev'
Requires-Dist: python-dotenv ; extra == 'dev'
Requires-Dist: sphinx ; extra == 'dev'
Provides-Extra: docs
Requires-Dist: numpydoc ; extra == 'docs'
Requires-Dist: Pallets-Sphinx-Themes ; extra == 'docs'
Requires-Dist: sphinx ; extra == 'docs'
